[
  {
    "id": "m5Wj2ThjA14",
    "slug": "m5Wj2ThjA14",
    "created_at": "2023-04-28T12:59:36Z",
    "updated_at": "2023-09-10T06:32:47Z",
    "promoted_at": null,
    "width": 5595,
    "height": 8393,
    "color": "#c0a6a6",
    "blur_hash": "LPD];#EN%3R*Oeo$ofWr0mt8R*og",
    "description": "Yellow desert wildflowers, Nature Reserve – NEOM, Saudi Arabia | The NEOM Nature Reserve region is being designed to deliver protection and restoration of biodiversity across 95% of NEOM.",
    "alt_description": "a man with a backpack is running on rocks",
    "breadcrumbs": [],
    "urls": {
      "raw": "https://images.unsplash.com/photo-1682686581797-21ec383ead02?ixid=M3w0OTg2NjJ8MXwxfGFsbHwxfHx8fHx8Mnx8MTY5NDM0MTM2MHw\u0026ixlib=rb-4.0.3",
      "full": "https://images.unsplash.com/photo-1682686581797-21ec383ead02?crop=entropy\u0026cs=srgb\u0026fm=jpg\u0026ixid=M3w0OTg2NjJ8MXwxfGFsbHwxfHx8fHx8Mnx8MTY5NDM0MTM2MHw\u0026ixlib=rb-4.0.3\u0026q=85",
      "regular": "https://images.unsplash.com/photo-1682686581797-21ec383ead02?crop=entropy\u0026cs=tinysrgb\u0026fit=max\u0026fm=jpg\u0026ixid=M3w0OTg2NjJ8MXwxfGFsbHwxfHx8fHx8Mnx8MTY5NDM0MTM2MHw\u0026ixlib=rb-4.0.3\u0026q=80\u0026w=1080",
      "small": "https://images.unsplash.com/photo-1682686581797-21ec383ead02?crop=entropy\u0026cs=tinysrgb\u0026fit=max\u0026fm=jpg\u0026ixid=M3w0OTg2NjJ8MXwxfGFsbHwxfHx8fHx8Mnx8MTY5NDM0MTM2MHw\u0026ixlib=rb-4.0.3\u0026q=80\u0026w=400",
      "thumb": "https://images.unsplash.com/photo-1682686581797-21ec383ead02?crop=entropy\u0026cs=tinysrgb\u0026fit=max\u0026fm=jpg\u0026ixid=M3w0OTg2NjJ8MXwxfGFsbHwxfHx8fHx8Mnx8MTY5NDM0MTM2MHw\u0026ixlib=rb-4.0.3\u0026q=80\u0026w=200",
      "small_s3": "https://s3.us-west-2.amazonaws.com/images.unsplash.com/small/photo-1682686581797-21ec383ead02"
    },
    "links": {
      "self": "https://api.unsplash.com/photos/m5Wj2ThjA14",
      "html": "https://unsplash.com/photos/m5Wj2ThjA14",
      "download": "https://unsplash.com/photos/m5Wj2ThjA14/download?ixid=M3w0OTg2NjJ8MXwxfGFsbHwxfHx8fHx8Mnx8MTY5NDM0MTM2MHw",
      "download_location": "https://api.unsplash.com/photos/m5Wj2ThjA14/download?ixid=M3w0OTg2NjJ8MXwxfGFsbHwxfHx8fHx8Mnx8MTY5NDM0MTM2MHw"
    },
    "likes": 89,
    "liked_by_user": false,
    "current_user_collections": [],
    "sponsorship": {
      "impression_urls": [
        "https://secure.insightexpressai.com/adServer/adServerESI.aspx?script=false\u0026bannerID=11515513\u0026rnd=[timestamp]\u0026redir=https://secure.insightexpressai.com/adserver/1pixel.gif",
        "https://secure.insightexpressai.com/adServer/adServerESI.aspx?script=false\u0026bannerID=11515716\u0026rnd=[timestamp]\u0026redir=https://secure.insightexpressai.com/adserver/1pixel.gif"
      ],
      "tagline": "Made to Change",
      "tagline_url": "https://www.neom.com/en-us?utm_source=unsplash\u0026utm_medium=referral",
      "sponsor": {
        "id": "mYizSrdJkkU",
        "updated_at": "2023-09-10T09:29:46Z",
        "username": "neom",
        "name": "NEOM",
        "first_name": "NEOM",
        "last_name": null,
        "twitter_username": "neom",
        "portfolio_url": "http://www.neom.com",
        "bio": "Located in the northwest of Saudi Arabia, NEOM’s diverse climate offers both sun-soaked beaches and snow-capped mountains. NEOM’s unique location will provide residents with enhanced livability while protecting 95% of the natural landscape.",
        "location": "NEOM, Saudi Arabia",
        "links": {
          "self": "https://api.unsplash.com/users/neom",
          "html": "https://unsplash.com/@neom",
          "photos": "https://api.unsplash.com/users/neom/photos",
          "likes": "https://api.unsplash.com/users/neom/likes",
          "portfolio": "https://api.unsplash.com/users/neom/portfolio",
          "following": "https://api.unsplash.com/users/neom/following",
          "followers": "https://api.unsplash.com/users/neom/followers"
        },
        "profile_image": {
          "small": "https://images.unsplash.com/profile-1679489218992-ebe823c797dfimage?ixlib=rb-4.0.3\u0026crop=faces\u0026fit=crop\u0026w=32\u0026h=32",
          "medium": "https://images.unsplash.com/profile-1679489218992-ebe823c797dfimage?ixlib=rb-4.0.3\u0026crop=faces\u0026fit=crop\u0026w=64\u0026h=64",
          "large": "https://images.unsplash.com/profile-1679489218992-ebe823c797dfimage?ixlib=rb-4.0.3\u0026crop=faces\u0026fit=crop\u0026w=128\u0026h=128"
        },
        "instagram_username": "discoverneom",
        "total_collections": 7,
        "total_likes": 0,
        "total_photos": 202,
        "accepted_tos": true,
        "for_hire": false,
        "social": {
          "instagram_username": "discoverneom",
          "portfolio_url": "http://www.neom.com",
          "twitter_username": "neom",
          "paypal_email": null
        }
      }
    },
    "topic_submissions": {},
    "user": {
      "id": "mYizSrdJkkU",
      "updated_at": "2023-09-10T09:29:46Z",
      "username": "neom",
      "name": "NEOM",
      "first_name": "NEOM",
      "last_name": null,
      "twitter_username": "neom",
      "portfolio_url": "http://www.neom.com",
      "bio": "Located in the northwest of Saudi Arabia, NEOM’s diverse climate offers both sun-soaked beaches and snow-capped mountains. NEOM’s unique location will provide residents with enhanced livability while protecting 95% of the natural landscape.",
      "location": "NEOM, Saudi Arabia",
      "links": {
        "self": "https://api.unsplash.com/users/neom",
        "html": "https://unsplash.com/@neom",
        "photos": "https://api.unsplash.com/users/neom/photos",
        "likes": "https://api.unsplash.com/users/neom/likes",
        "portfolio": "https://api.unsplash.com/users/neom/portfolio",
        "following": "https://api.unsplash.com/users/neom/following",
        "followers": "https://api.unsplash.com/users/neom/followers"
      },
      "profile_image": {
        "small": "https://images.unsplash.com/profile-1679489218992-ebe823c797dfimage?ixlib=rb-4.0.3\u0026crop=faces\u0026fit=crop\u0026w=32\u0026h=32",
        "medium": "https://images.unsplash.com/profile-1679489218992-ebe823c797dfimage?ixlib=rb-4.0.3\u0026crop=faces\u0026fit=crop\u0026w=64\u0026h=64",
        "large": "https://images.unsplash.com/profile-1679489218992-ebe823c797dfimage?ixlib=rb-4.0.3\u0026crop=faces\u0026fit=crop\u0026w=128\u0026h=128"
      },
      "instagram_username": "discoverneom",
      "total_collections": 7,
      "total_likes": 0,
      "total_photos": 202,
      "accepted_tos": true,
      "for_hire": false,
      "social": {
        "instagram_username": "discoverneom",
        "portfolio_url": "http://www.neom.com",
        "twitter_username": "neom",
        "paypal_email": null
      }
    }
  },
  {
    "id": "CkAIUTWjZsc",
    "slug": "a-picture-of-a-painting-with-writing-on-it-CkAIUTWjZsc",
    "created_at": "2023-07-15T21:07:22Z",
    "updated_at": "2023-09-10T07:39:06Z",
    "promoted_at": "2023-09-09T17:40:07Z",
    "width": 4160,
    "height": 6240,
    "color": "#737359",
    "blur_hash": "LDH1F:T_IC=so}J.sTni~9-TR+f+",
    "description": null,
    "alt_description": "a picture of a painting with writing on it",
    "breadcrumbs": [],
    "urls": {
      "raw": "https://images.unsplash.com/photo-1689455231345-54a5126d9826?ixid=M3w0OTg2NjJ8MHwxfGFsbHwyfHx8fHx8Mnx8MTY5NDM0MTM2MHw\u0026ixlib=rb-4.0.3",
      "full": "https://images.unsplash.com/photo-1689455231345-54a5126d9826?crop=entropy\u0026cs=srgb\u0026fm=jpg\u0026ixid=M3w0OTg2NjJ8MHwxfGFsbHwyfHx8fHx8Mnx8MTY5NDM0MTM2MHw\u0026ixlib=rb-4.0.3\u0026q=85",
      "regular": "https://images.unsplash.com/photo-1689455231345-54a5126d9826?crop=entropy\u0026cs=tinysrgb\u0026fit=max\u0026fm=jpg\u0026ixid=M3w0OTg2NjJ8MHwxfGFsbHwyfHx8fHx8Mnx8MTY5NDM0MTM2MHw\u0026ixlib=rb-4.0.3\u0026q=80\u0026w=1080",
      "small": "https://images.unsplash.com/photo-1689455231345-54a5126d9826?crop=entropy\u0026cs=tinysrgb\u0026fit=max\u0026fm=jpg\u0026ixid=M3w0OTg2NjJ8MHwxfGFsbHwyfHx8fHx8Mnx8MTY5NDM0MTM2MHw\u0026ixlib=rb-4.0.3\u0026q=80\u0026w=400",
      "thumb": "https://images.unsplash.com/photo-1689455231345-54a5126d9826?crop=entropy\u0026cs=tinysrgb\u0026fit=max\u0026fm=jpg\u0026ixid=M3w0OTg2NjJ8MHwxfGFsbHwyfHx8fHx8Mnx8MTY5NDM0MTM2MHw\u0026ixlib=rb-4.0.3\u0026q=80\u0026w=200",
      "small_s3": "https://s3.us-west-2.amazonaws.com/images.unsplash.com/small/photo-1689455231345-54a5126d9826"
    },
    "links": {
      "self": "https://api.unsplash.com/photos/a-picture-of-a-painting-with-writing-on-it-CkAIUTWjZsc",
      "html": "https://unsplash.com/photos/a-picture-of-a-painting-with-writing-on-it-CkAIUTWjZsc",
      "download": "https://unsplash.com/photos/CkAIUTWjZsc/download?ixid=M3w0OTg2NjJ8MHwxfGFsbHwyfHx8fHx8Mnx8MTY5NDM0MTM2MHw",
      "download_location": "https://api.unsplash.com/photos/CkAIUTWjZsc/download?ixid=M3w0OTg2NjJ8MHwxfGFsbHwyfHx8fHx8Mnx8MTY5NDM0MTM2MHw"
    },
    "likes": 63,
    "liked_by_user": false,
    "current_user_collections": [],
    "sponsorship": null,
    "topic_submissions": {},
    "user": {
      "id": "Z2MQ--6zu0s",
      "updated_at": "2023-09-09T17:40:07Z",
      "username": "zapyatkina",
      "name": "Kseniia Zapiatkina",
      "first_name": "Kseniia",
      "last_name": "Zapiatkina",
      "twitter_username": null,
      "portfolio_url": null,
      "bio": null,
      "location": null,
      "links": {
        "self": "https://api.unsplash.com/users/zapyatkina",
        "html": "https://unsplash.com/@zapyatkina",
        "photos": "https://api.unsplash.com/users/zapyatkina/photos",
        "likes": "https://api.unsplash.com/users/zapyatkina/likes",
        "portfolio": "https://api.unsplash.com/users/zapyatkina/portfolio",
        "following": "https://api.unsplash.com/users/zapyatkina/following",
        "followers": "https://api.unsplash.com/users/zapyatkina/followers"
      },
      "profile_image": {
        "small": "https://images.unsplash.com/profile-1688499020483-de3f1345eeed?ixlib=rb-4.0.3\u0026crop=faces\u0026fit=crop\u0026w=32\u0026h=32",
        "medium": "https://images.unsplash.com/profile-1688499020483-de3f1345eeed?ixlib=rb-4.0.3\u0026crop=faces\u0026fit=crop\u0026w=64\u0026h=64",
        "large": "https://images.unsplash.com/profile-1688499020483-de3f1345eeed?ixlib=rb-4.0.3\u0026crop=faces\u0026fit=crop\u0026w=128\u0026h=128"
      },
      "instagram_username": "albuferas",
      "total_collections": 0,
      "total_likes": 55,
      "total_photos": 98,
      "accepted_tos": true,
      "for_hire": false,
      "social": {
        "instagram_username": "albuferas",
        "portfolio_url": null,
        "twitter_username": null,
        "paypal_email": null
      }
    }
  },
  {
    "id": "XwTpaM9I11g",
    "slug": "a-baby-sitting-on-a-bed-with-white-sheets-XwTpaM9I11g",
    "created_at": "2023-09-09T04:05:08Z",
    "updated_at": "2023-09-10T10:00:05Z",
    "promoted_at": "2023-09-09T17:32:01Z",
    "width": 4480,
    "height": 6720,
    "color": "#d9d9d9",
    "blur_hash": "LKOgA__3Nexu4mxuWUWAOBRiVsWA",
    "description": "baby, portrait, people, little boy, bedding, little one, child",
    "alt_description": "a baby sitting on a bed with white sheets",
    "breadcrumbs": [],
    "urls": {
      "raw": "https://images.unsplash.com/photo-1694231664712-91e992b4d4a8?ixid=M3w0OTg2NjJ8MHwxfGFsbHwzfHx8fHx8Mnx8MTY5NDM0MTM2MHw\u0026ixlib=rb-4.0.3",
      "full": "https://images.unsplash.com/photo-1694231664712-91e992b4d4a8?crop=entropy\u0026cs=srgb\u0026fm=jpg\u0026ixid=M3w0OTg2NjJ8MHwxfGFsbHwzfHx8fHx8Mnx8MTY5NDM0MTM2MHw\u0026ixlib=rb-4.0.3\u0026q=85",
      "regular": "https://images.unsplash.com/photo-1694231664712-91e992b4d4a8?crop=entropy\u0026cs=tinysrgb\u0026fit=max\u0026fm=jpg\u0026ixid=M3w0OTg2NjJ8MHwxfGFsbHwzfHx8fHx8Mnx8MTY5NDM0MTM2MHw\u0026ixlib=rb-4.0.3\u0026q=80\u0026w=1080",
      "small": "https://images.unsplash.com/photo-1694231664712-91e992b4d4a8?crop=entropy\u0026cs=tinysrgb\u0026fit=max\u0026fm=jpg\u0026ixid=M3w0OTg2NjJ8MHwxfGFsbHwzfHx8fHx8Mnx8MTY5NDM0MTM2MHw\u0026ixlib=rb-4.0.3\u0026q=80\u0026w=400",
      "thumb": "https://images.unsplash.com/photo-1694231664712-91e992b4d4a8?crop=entropy\u0026cs=tinysrgb\u0026fit=max\u0026fm=jpg\u0026ixid=M3w0OTg2NjJ8MHwxfGFsbHwzfHx8fHx8Mnx8MTY5NDM0MTM2MHw\u0026ixlib=rb-4.0.3\u0026q=80\u0026w=200",
      "small_s3": "https://s3.us-west-2.amazonaws.com/images.unsplash.com/small/photo-1694231664712-91e992b4d4a8"
    },
    "links": {
      "self": "https://api.unsplash.com/photos/a-baby-sitting-on-a-bed-with-white-sheets-XwTpaM9I11g",
      "html": "https://unsplash.com/photos/a-baby-sitting-on-a-bed-with-white-sheets-XwTpaM9I11g",
      "download": "https://unsplash.com/photos/XwTpaM9I11g/download?ixid=M3w0OTg2NjJ8MHwxfGFsbHwzfHx8fHx8Mnx8MTY5NDM0MTM2MHw",
      "download_location": "https://api.unsplash.com/photos/XwTpaM9I11g/download?ixid=M3w0OTg2NjJ8MHwxfGFsbHwzfHx8fHx8Mnx8MTY5NDM0MTM2MHw"
    },
    "likes": 14,
    "liked_by_user": false,
    "current_user_collections": [],
    "sponsorship": null,
    "topic_submissions": {},
    "user": {
      "id": "kQXGKIpenns",
      "updated_at": "2023-09-10T01:21:19Z",
      "username": "jkalen71",
      "name": "Jennifer Kalenberg",
      "first_name": "Jennifer",
      "last_name": "Kalenberg",
      "twitter_username": null,
      "portfolio_url": null,
      "bio": null,
      "location": null,
      "links": {
        "self": "https://api.unsplash.com/users/jkalen71",
        "html": "https://unsplash.com/@jkalen71",
        "photos": "https://api.unsplash.com/users/jkalen71/photos",
        "likes": "https://api.unsplash.com/users/jkalen71/likes",
        "portfolio": "https://api.unsplash.com/users/jkalen71/portfolio",
        "following": "https://api.unsplash.com/users/jkalen71/following",
        "followers": "https://api.unsplash.com/users/jkalen71/followers"
      },
      "profile_image": {
        "small": "https://images.unsplash.com/profile-fb-1683581327-58f8acc134ef.jpg?ixlib=rb-4.0.3\u0026crop=faces\u0026fit=crop\u0026w=32\u0026h=32",
        "medium": "https://images.unsplash.com/profile-fb-1683581327-58f8acc134ef.jpg?ixlib=rb-4.0.3\u0026crop=faces\u0026fit=crop\u0026w=64\u0026h=64",
        "large": "https://images.unsplash.com/profile-fb-1683581327-58f8acc134ef.jpg?ixlib=rb-4.0.3\u0026crop=faces\u0026fit=crop\u0026w=128\u0026h=128"
      },
      "instagram_username": null,
      "total_collections": 0,
      "total_likes": 157,
      "total_photos": 52,
      "accepted_tos": true,
      "for_hire": true,
      "social": {
        "instagram_username": null,
        "portfolio_url": null,
        "twitter_username": null,
        "paypal_email": null
      }
    }
  },
  {
    "id": "S_6iK53Z42g",
    "slug": "a-desk-with-a-lamp-clock-and-other-items-on-it-S_6iK53Z42g",
    "created_at": "2023-09-08T10:23:23Z",
    "updated_at": "2023-09-10T08:37:30Z",
    "promoted_at": "2023-09-09T17:24:01Z",
    "width": 4425,
    "height": 5532,
    "color": "#d9c0a6",
    "blur_hash": "LmI;ePIqs.fk0LWqfPWC%MxZWCbH",
    "description": null,
    "alt_description": "a desk with a lamp, clock, and other items on it",
    "breadcrumbs": [],
    "urls": {
      "raw": "https://images.unsplash.com/photo-1694168475919-dc385a48b99c?ixid=M3w0OTg2NjJ8MHwxfGFsbHw0fHx8fHx8Mnx8MTY5NDM0MTM2MHw\u0026ixlib=rb-4.0.3",
      "full": "https://images.unsplash.com/photo-1694168475919-dc385a48b99c?crop=entropy\u0026cs=srgb\u0026fm=jpg\u0026ixid=M3w0OTg2NjJ8MHwxfGFsbHw0fHx8fHx8Mnx8MTY5NDM0MTM2MHw\u0026ixlib=rb-4.0.3\u0026q=85",
      "regular": "https://images.unsplash.com/photo-1694168475919-dc385a48b99c?crop=entropy\u0026cs=tinysrgb\u0026fit=max\u0026fm=jpg\u0026ixid=M3w0OTg2NjJ8MHwxfGFsbHw0fHx8fHx8Mnx8MTY5NDM0MTM2MHw\u0026ixlib=rb-4.0.3\u0026q=80\u0026w=1080",
      "small": "https://images.unsplash.com/photo-1694168475919-dc385a48b99c?crop=entropy\u0026cs=tinysrgb\u0026fit=max\u0026fm=jpg\u0026ixid=M3w0OTg2NjJ8MHwxfGFsbHw0fHx8fHx8Mnx8MTY5NDM0MTM2MHw\u0026ixlib=rb-4.0.3\u0026q=80\u0026w=400",
      "thumb": "https://images.unsplash.com/photo-1694168475919-dc385a48b99c?crop=entropy\u0026cs=tinysrgb\u0026fit=max\u0026fm=jpg\u0026ixid=M3w0OTg2NjJ8MHwxfGFsbHw0fHx8fHx8Mnx8MTY5NDM0MTM2MHw\u0026ixlib=rb-4.0.3\u0026q=80\u0026w=200",
      "small_s3": "https://s3.us-west-2.amazonaws.com/images.unsplash.com/small/photo-1694168475919-dc385a48b99c"
    },
    "links": {
      "self": "https://api.unsplash.com/photos/a-desk-with-a-lamp-clock-and-other-items-on-it-S_6iK53Z42g",
      "html": "https://unsplash.com/photos/a-desk-with-a-lamp-clock-and-other-items-on-it-S_6iK53Z42g",
      "download": "https://unsplash.com/photos/S_6iK53Z42g/download?ixid=M3w0OTg2NjJ8MHwxfGFsbHw0fHx8fHx8Mnx8MTY5NDM0MTM2MHw",
      "download_location": "https://api.unsplash.com/photos/S_6iK53Z42g/download?ixid=M3w0OTg2NjJ8MHwxfGFsbHw0fHx8fHx8Mnx8MTY5NDM0MTM2MHw"
    },
    "likes": 20,
    "liked_by_user": false,
    "current_user_collections": [],
    "sponsorship": null,
    "topic_submissions": {},
    "user": {
      "id": "CU0kB_aF_X4",
      "updated_at": "2023-09-09T22:01:51Z",
      "username": "maybejensen",
      "name": "Lasse Jensen",
      "first_name": "Lasse",
      "last_name": "Jensen",
      "twitter_username": "maybejensen",
      "portfolio_url": "http://maybejensen.com",
      "bio": "Copenhagen-based photographer focusing on brand and lifestyle content. Visit my website for more info",
      "location": "Denmark",
      "links": {
        "self": "https://api.unsplash.com/users/maybejensen",
        "html": "https://unsplash.com/@maybejensen",
        "photos": "https://api.unsplash.com/users/maybejensen/photos",
        "likes": "https://api.unsplash.com/users/maybejensen/likes",
        "portfolio": "https://api.unsplash.com/users/maybejensen/portfolio",
        "following": "https://api.unsplash.com/users/maybejensen/following",
        "followers": "https://api.unsplash.com/users/maybejensen/followers"
      },
      "profile_image": {
        "small": "https://images.unsplash.com/profile-1612347312199-765b00401715image?ixlib=rb-4.0.3\u0026crop=faces\u0026fit=crop\u0026w=32\u0026h=32",
        "medium": "https://images.unsplash.com/profile-1612347312199-765b00401715image?ixlib=rb-4.0.3\u0026crop=faces\u0026fit=crop\u0026w=64\u0026h=64",
        "large": "https://images.unsplash.com/profile-1612347312199-765b00401715image?ixlib=rb-4.0.3\u0026crop=faces\u0026fit=crop\u0026w=128\u0026h=128"
      },
      "instagram_username": "maybejensen",
      "total_collections": 6,
      "total_likes": 307,
      "total_photos": 153,
      "accepted_tos": true,
      "for_hire": true,
      "social": {
        "instagram_username": "maybejensen",
        "portfolio_url": "http://maybejensen.com",
        "twitter_username": "maybejensen",
        "paypal_email": null
      }
    }
  },
  {
    "id": "hr-VSXjkuS8",
    "slug": "a-person-sitting-at-a-table-with-a-plate-of-food-hr-VSXjkuS8",
    "created_at": "2023-09-08T10:23:23Z",
    "updated_at": "2023-09-10T06:35:17Z",
    "promoted_at": "2023-09-09T17:08:01Z",
    "width": 4672,
    "height": 7008,
    "color": "#c0c0c0",
    "blur_hash": "LOLWtzw@%Lx]DNIToctSyFIpRit8",
    "description": null,
    "alt_description": "a person sitting at a table with a plate of food",
    "breadcrumbs": [],
    "urls": {
      "raw": "https://images.unsplash.com/photo-1694168502628-b95247bb6a09?ixid=M3w0OTg2NjJ8MHwxfGFsbHw1fHx8fHx8Mnx8MTY5NDM0MTM2MHw\u0026ixlib=rb-4.0.3",
      "full": "https://images.unsplash.com/photo-1694168502628-b95247bb6a09?crop=entropy\u0026cs=srgb\u0026fm=jpg\u0026ixid=M3w0OTg2NjJ8MHwxfGFsbHw1fHx8fHx8Mnx8MTY5NDM0MTM2MHw\u0026ixlib=rb-4.0.3\u0026q=85",
      "regular": "https://images.unsplash.com/photo-1694168502628-b95247bb6a09?crop=entropy\u0026cs=tinysrgb\u0026fit=max\u0026fm=jpg\u0026ixid=M3w0OTg2NjJ8MHwxfGFsbHw1fHx8fHx8Mnx8MTY5NDM0MTM2MHw\u0026ixlib=rb-4.0.3\u0026q=80\u0026w=1080",
      "small": "https://images.unsplash.com/photo-1694168502628-b95247bb6a09?crop=entropy\u0026cs=tinysrgb\u0026fit=max\u0026fm=jpg\u0026ixid=M3w0OTg2NjJ8MHwxfGFsbHw1fHx8fHx8Mnx8MTY5NDM0MTM2MHw\u0026ixlib=rb-4.0.3\u0026q=80\u0026w=400",
      "thumb": "https://images.unsplash.com/photo-1694168502628-b95247bb6a09?crop=entropy\u0026cs=tinysrgb\u0026fit=max\u0026fm=jpg\u0026ixid=M3w0OTg2NjJ8MHwxfGFsbHw1fHx8fHx8Mnx8MTY5NDM0MTM2MHw\u0026ixlib=rb-4.0.3\u0026q=80\u0026w=200",
      "small_s3": "https://s3.us-west-2.amazonaws.com/images.unsplash.com/small/photo-1694168502628-b95247bb6a09"
    },
    "links": {
      "self": "https://api.unsplash.com/photos/a-person-sitting-at-a-table-with-a-plate-of-food-hr-VSXjkuS8",
      "html": "https://unsplash.com/photos/a-person-sitting-at-a-table-with-a-plate-of-food-hr-VSXjkuS8",
      "download": "https://unsplash.com/photos/hr-VSXjkuS8/download?ixid=M3w0OTg2NjJ8MHwxfGFsbHw1fHx8fHx8Mnx8MTY5NDM0MTM2MHw",
      "download_location": "https://api.unsplash.com/photos/hr-VSXjkuS8/download?ixid=M3w0OTg2NjJ8MHwxfGFsbHw1fHx8fHx8Mnx8MTY5NDM0MTM2MHw"
    },
    "likes": 14,
    "liked_by_user": false,
    "current_user_collections": [],
    "sponsorship": null,
    "topic_submissions": {},
    "user": {
      "id": "CU0kB_aF_X4",
      "updated_at": "2023-09-09T22:01:51Z",
      "username": "maybejensen",
      "name": "Lasse Jensen",
      "first_name": "Lasse",
      "last_name": "Jensen",
      "twitter_username": "maybejensen",
      "portfolio_url": "http://maybejensen.com",
      "bio": "Copenhagen-based photographer focusing on brand and lifestyle content. Visit my website for more info",
      "location": "Denmark",
      "links": {
        "self": "https://api.unsplash.com/users/maybejensen",
        "html": "https://unsplash.com/@maybejensen",
        "photos": "https://api.unsplash.com/users/maybejensen/photos",
        "likes": "https://api.unsplash.com/users/maybejensen/likes",
        "portfolio": "https://api.unsplash.com/users/maybejensen/portfolio",
        "following": "https://api.unsplash.com/users/maybejensen/following",
        "followers": "https://api.unsplash.com/users/maybejensen/followers"
      },
      "profile_image": {
        "small": "https://images.unsplash.com/profile-1612347312199-765b00401715image?ixlib=rb-4.0.3\u0026crop=faces\u0026fit=crop\u0026w=32\u0026h=32",
        "medium": "https://images.unsplash.com/profile-1612347312199-765b00401715image?ixlib=rb-4.0.3\u0026crop=faces\u0026fit=crop\u0026w=64\u0026h=64",
        "large": "https://images.unsplash.com/profile-1612347312199-765b00401715image?ixlib=rb-4.0.3\u0026crop=faces\u0026fit=crop\u0026w=128\u0026h=128"
      },
      "instagram_username": "maybejensen",
      "total_collections": 6,
      "total_likes": 307,
      "total_photos": 153,
      "accepted_tos": true,
      "for_hire": true,
      "social": {
        "instagram_username": "maybejensen",
        "portfolio_url": "http://maybejensen.com",
        "twitter_username": "maybejensen",
        "paypal_email": null
      }
    }
  },
  {
    "id": "Xm1wdkNUwrY",
    "slug": "Xm1wdkNUwrY",
    "created_at": "2023-05-02T06:42:00Z",
    "updated_at": "2023-09-09T13:36:29Z",
    "promoted_at": null,
    "width": 8688,
    "height": 5792,
    "color": "#f3d9c0",
    "blur_hash": "L,LD0;NaRkxZ~pf6aeWVtljYjZWC",
    "description": "Amongst expansive red sands and spectacular sandstone rock formations, Hisma Desert – NEOM, Saudi Arabia | The NEOM Nature Reserve region is being designed to deliver protection and restoration of biodiversity across 95% of NEOM.",
    "alt_description": "a man standing in front of a desert landscape",
    "breadcrumbs": [],
    "urls": {
      "raw": "https://images.unsplash.com/photo-1683009427479-c7e36bbb7bca?ixid=M3w0OTg2NjJ8MXwxfGFsbHw2fHx8fHx8Mnx8MTY5NDM0MTM2MHw\u0026ixlib=rb-4.0.3",
      "full": "https://images.unsplash.com/photo-1683009427479-c7e36bbb7bca?crop=entropy\u0026cs=srgb\u0026fm=jpg\u0026ixid=M3w0OTg2NjJ8MXwxfGFsbHw2fHx8fHx8Mnx8MTY5NDM0MTM2MHw\u0026ixlib=rb-4.0.3\u0026q=85",
      "regular": "https://images.unsplash.com/photo-1683009427479-c7e36bbb7bca?crop=entropy\u0026cs=tinysrgb\u0026fit=max\u0026fm=jpg\u0026ixid=M3w0OTg2NjJ8MXwxfGFsbHw2fHx8fHx8Mnx8MTY5NDM0MTM2MHw\u0026ixlib=rb-4.0.3\u0026q=80\u0026w=1080",
      "small": "https://images.unsplash.com/photo-1683009427479-c7e36bbb7bca?crop=entropy\u0026cs=tinysrgb\u0026fit=max\u0026fm=jpg\u0026ixid=M3w0OTg2NjJ8MXwxfGFsbHw2fHx8fHx8Mnx8MTY5NDM0MTM2MHw\u0026ixlib=rb-4.0.3\u0026q=80\u0026w=400",
      "thumb": "https://images.unsplash.com/photo-1683009427479-c7e36bbb7bca?crop=entropy\u0026cs=tinysrgb\u0026fit=max\u0026fm=jpg\u0026ixid=M3w0OTg2NjJ8MXwxfGFsbHw2fHx8fHx8Mnx8MTY5NDM0MTM2MHw\u0026ixlib=rb-4.0.3\u0026q=80\u0026w=200",
      "small_s3": "https://s3.us-west-2.amazonaws.com/images.unsplash.com/small/photo-1683009427479-c7e36bbb7bca"
    },
    "links": {
      "self": "https://api.unsplash.com/photos/Xm1wdkNUwrY",
      "html": "https://unsplash.com/photos/Xm1wdkNUwrY",
      "download": "https://unsplash.com/photos/Xm1wdkNUwrY/download?ixid=M3w0OTg2NjJ8MXwxfGFsbHw2fHx8fHx8Mnx8MTY5NDM0MTM2MHw",
      "download_location": "https://api.unsplash.com/photos/Xm1wdkNUwrY/download?ixid=M3w0OTg2NjJ8MXwxfGFsbHw2fHx8fHx8Mnx8MTY5NDM0MTM2MHw"
    },
    "likes": 120,
    "liked_by_user": false,
    "current_user_collections": [],
    "sponsorship": {
      "impression_urls": [
        "https://secure.insightexpressai.com/adServer/adServerESI.aspx?script=false\u0026bannerID=11515517\u0026rnd=[timestamp]\u0026redir=https://secure.insightexpressai.com/adserver/1pixel.gif",
        "https://secure.insightexpressai.com/adServer/adServerESI.aspx?script=false\u0026bannerID=11515720\u0026rnd=[timestamp]\u0026redir=https://secure.insightexpressai.com/adserver/1pixel.gif"
      ],
      "tagline": "Made to Change",
      "tagline_url": "https://www.neom.com/en-us?utm_source=unsplash\u0026utm_medium=referral",
      "sponsor": {
        "id": "mYizSrdJkkU",
        "updated_at": "2023-09-10T09:29:46Z",
        "username": "neom",
        "name": "NEOM",
        "first_name": "NEOM",
        "last_name": null,
        "twitter_username": "neom",
        "portfolio_url": "http://www.neom.com",
        "bio": "Located in the northwest of Saudi Arabia, NEOM’s diverse climate offers both sun-soaked beaches and snow-capped mountains. NEOM’s unique location will provide residents with enhanced livability while protecting 95% of the natural landscape.",
        "location": "NEOM, Saudi Arabia",
        "links": {
          "self": "https://api.unsplash.com/users/neom",
          "html": "https://unsplash.com/@neom",
          "photos": "https://api.unsplash.com/users/neom/photos",
          "likes": "https://api.unsplash.com/users/neom/likes",
          "portfolio": "https://api.unsplash.com/users/neom/portfolio",
          "following": "https://api.unsplash.com/users/neom/following",
          "followers": "https://api.unsplash.com/users/neom/followers"
        },
        "profile_image": {
          "small": "https://images.unsplash.com/profile-1679489218992-ebe823c797dfimage?ixlib=rb-4.0.3\u0026crop=faces\u0026fit=crop\u0026w=32\u0026h=32",
          "medium": "https://images.unsplash.com/profile-1679489218992-ebe823c797dfimage?ixlib=rb-4.0.3\u0026crop=faces\u0026fit=crop\u0026w=64\u0026h=64",
          "large": "https://images.unsplash.com/profile-1679489218992-ebe823c797dfimage?ixlib=rb-4.0.3\u0026crop=faces\u0026fit=crop\u0026w=128\u0026h=128"
        },
        "instagram_username": "discoverneom",
        "total_collections": 7,
        "total_likes": 0,
        "total_photos": 202,
        "accepted_tos": true,
        "for_hire": false,
        "social": {
          "instagram_username": "discoverneom",
          "portfolio_url": "http://www.neom.com",
          "twitter_username": "neom",
          "paypal_email": null
        }
      }
    },
    "topic_submissions": {},
    "user": {
      "id": "mYizSrdJkkU",
      "updated_at": "2023-09-10T09:29:46Z",
      "username": "neom",
      "name": "NEOM",
      "first_name": "NEOM",
      "last_name": null,
      "twitter_username": "neom",
      "portfolio_url": "http://www.neom.com",
      "bio": "Located in the northwest of Saudi Arabia, NEOM’s diverse climate offers both sun-soaked beaches and snow-capped mountains. NEOM’s unique location will provide residents with enhanced livability while protecting 95% of the natural landscape.",
      "location": "NEOM, Saudi Arabia",
      "links": {
        "self": "https://api.unsplash.com/users/neom",
        "html": "https://unsplash.com/@neom",
        "photos": "https://api.unsplash.com/users/neom/photos",
        "likes": "https://api.unsplash.com/users/neom/likes",
        "portfolio": "https://api.unsplash.com/users/neom/portfolio",
        "following": "https://api.unsplash.com/users/neom/following",
        "followers": "https://api.unsplash.com/users/neom/followers"
      },
      "profile_image": {
        "small": "https://images.unsplash.com/profile-1679489218992-ebe823c797dfimage?ixlib=rb-4.0.3\u0026crop=faces\u0026fit=crop\u0026w=32\u0026h=32",
        "medium": "https://images.unsplash.com/profile-1679489218992-ebe823c797dfimage?ixlib=rb-4.0.3\u0026crop=faces\u0026fit=crop\u0026w=64\u0026h=64",
        "large": "https://images.unsplash.com/profile-1679489218992-ebe823c797dfimage?ixlib=rb-4.0.3\u0026crop=faces\u0026fit=crop\u0026w=128\u0026h=128"
      },
      "instagram_username": "discoverneom",
      "total_collections": 7,
      "total_likes": 0,
      "total_photos": 202,
      "accepted_tos": true,
      "for_hire": false,
      "social": {
        "instagram_username": "discoverneom",
        "portfolio_url": "http://www.neom.com",
        "twitter_username": "neom",
        "paypal_email": null
      }
    }
  },
  {
    "id": "fLabFAAQc5w",
    "slug": "a-couple-of-people-swimming-in-the-ocean-at-sunset-fLabFAAQc5w",
    "created_at": "2023-09-09T11:46:29Z",
    "updated_at": "2023-09-09T19:37:01Z",
    "promoted_at": "2023-09-09T17:00:01Z",
    "width": 3936,
    "height": 5768,
    "color": "#d9c0a6",
    "blur_hash": "LmJG[*%1NGR*~Uoyaen$tQbHayj@",
    "description": "Catching waves.",
    "alt_description": "a couple of people swimming in the ocean at sunset",
    "breadcrumbs": [],
    "urls": {
      "raw": "https://images.unsplash.com/photo-1694259841577-caa97cde9518?ixid=M3w0OTg2NjJ8MHwxfGFsbHw3fHx8fHx8Mnx8MTY5NDM0MTM2MHw\u0026ixlib=rb-4.0.3",
      "full": "https://images.unsplash.com/photo-1694259841577-caa97cde9518?crop=entropy\u0026cs=srgb\u0026fm=jpg\u0026ixid=M3w0OTg2NjJ8MHwxfGFsbHw3fHx8fHx8Mnx8MTY5NDM0MTM2MHw\u0026ixlib=rb-4.0.3\u0026q=85",
      "regular": "https://images.unsplash.com/photo-1694259841577-caa97cde9518?crop=entropy\u0026cs=tinysrgb\u0026fit=max\u0026fm=jpg\u0026ixid=M3w0OTg2NjJ8MHwxfGFsbHw3fHx8fHx8Mnx8MTY5NDM0MTM2MHw\u0026ixlib=rb-4.0.3\u0026q=80\u0026w=1080",
      "small": "https://images.unsplash.com/photo-1694259841577-caa97cde9518?crop=entropy\u0026cs=tinysrgb\u0026fit=max\u0026fm=jpg\u0026ixid=M3w0OTg2NjJ8MHwxfGFsbHw3fHx8fHx8Mnx8MTY5NDM0MTM2MHw\u0026ixlib=rb-4.0.3\u0026q=80\u0026w=400",
      "thumb": "https://images.unsplash.com/photo-1694259841577-caa97cde9518?crop=entropy\u0026cs=tinysrgb\u0026fit=max\u0026fm=jpg\u0026ixid=M3w0OTg2NjJ8MHwxfGFsbHw3fHx8fHx8Mnx8MTY5NDM0MTM2MHw\u0026ixlib=rb-4.0.3\u0026q=80\u0026w=200",
      "small_s3": "https://s3.us-west-2.amazonaws.com/images.unsplash.com/small/photo-1694259841577-caa97cde9518"
    },
    "links": {
      "self": "https://api.unsplash.com/photos/a-couple-of-people-swimming-in-the-ocean-at-sunset-fLabFAAQc5w",
      "html": "https://unsplash.com/photos/a-couple-of-people-swimming-in-the-ocean-at-sunset-fLabFAAQc5w",
      "download": "https://unsplash.com/photos/fLabFAAQc5w/download?ixid=M3w0OTg2NjJ8MHwxfGFsbHw3fHx8fHx8Mnx8MTY5NDM0MTM2MHw",
      "download_location": "https://api.unsplash.com/photos/fLabFAAQc5w/download?ixid=M3w0OTg2NjJ8MHwxfGFsbHw3fHx8fHx8Mnx8MTY5NDM0MTM2MHw"
    },
    "likes": 47,
    "liked_by_user": false,
    "current_user_collections": [],
    "sponsorship": null,
    "topic_submissions": {},
    "user": {
      "id": "Qjuiw3yXjDI",
      "updated_at": "2023-09-10T10:00:18Z",
      "username": "jor9en",
      "name": "Jorgen Hendriksen",
      "first_name": "Jorgen",
      "last_name": "Hendriksen",
      "twitter_username": null,
      "portfolio_url": "http://www.jor9en.nl",
      "bio": "Hey, welcome to my Unsplash! 💻 Download my life in photos! For more pictures you can follow me on Instagram or check my website. 📷",
      "location": "The Netherlands",
      "links": {
        "self": "https://api.unsplash.com/users/jor9en",
        "html": "https://unsplash.com/@jor9en",
        "photos": "https://api.unsplash.com/users/jor9en/photos",
        "likes": "https://api.unsplash.com/users/jor9en/likes",
        "portfolio": "https://api.unsplash.com/users/jor9en/portfolio",
        "following": "https://api.unsplash.com/users/jor9en/following",
        "followers": "https://api.unsplash.com/users/jor9en/followers"
      },
      "profile_image": {
        "small": "https://images.unsplash.com/profile-1674497330038-c22eb3eee7fdimage?ixlib=rb-4.0.3\u0026crop=faces\u0026fit=crop\u0026w=32\u0026h=32",
        "medium": "https://images.unsplash.com/profile-1674497330038-c22eb3eee7fdimage?ixlib=rb-4.0.3\u0026crop=faces\u0026fit=crop\u0026w=64\u0026h=64",
        "large": "https://images.unsplash.com/profile-1674497330038-c22eb3eee7fdimage?ixlib=rb-4.0.3\u0026crop=faces\u0026fit=crop\u0026w=128\u0026h=128"
      },
      "instagram_username": "jor9en.nl",
      "total_collections": 4,
      "total_likes": 10,
      "total_photos": 486,
      "accepted_tos": true,
      "for_hire": true,
      "social": {
        "instagram_username": "jor9en.nl",
        "portfolio_url": "http://www.jor9en.nl",
        "twitter_username": null,
        "paypal_email": null
      }
    }
  },
  {
    "id": "vIQ3GV0XRFo",
    "slug": "a-view-of-the-eiffel-tower-from-below-vIQ3GV0XRFo",
    "created_at": "2023-09-08T16:39:12Z",
    "updated_at": "2023-09-10T10:00:04Z",
    "promoted_at": "2023-09-09T16:56:01Z",
    "width": 4000,
    "height": 6000,
    "color": "#d9d9d9",
    "blur_hash": "LnL#2ukCX9j[~qWVWCj[4:fQaef6",
    "description": "For any use contact me on Instagram (@gianpanto.arw)",
    "alt_description": "a view of the eiffel tower from below",
    "breadcrumbs": [],
    "urls": {
      "raw": "https://images.unsplash.com/photo-1694190941111-90065ded19d8?ixid=M3w0OTg2NjJ8MHwxfGFsbHw4fHx8fHx8Mnx8MTY5NDM0MTM2MHw\u0026ixlib=rb-4.0.3",
      "full": "https://images.unsplash.com/photo-1694190941111-90065ded19d8?crop=entropy\u0026cs=srgb\u0026fm=jpg\u0026ixid=M3w0OTg2NjJ8MHwxfGFsbHw4fHx8fHx8Mnx8MTY5NDM0MTM2MHw\u0026ixlib=rb-4.0.3\u0026q=85",
      "regular": "https://images.unsplash.com/photo-1694190941111-90065ded19d8?crop=entropy\u0026cs=tinysrgb\u0026fit=max\u0026fm=jpg\u0026ixid=M3w0OTg2NjJ8MHwxfGFsbHw4fHx8fHx8Mnx8MTY5NDM0MTM2MHw\u0026ixlib=rb-4.0.3\u0026q=80\u0026w=1080",
      "small": "https://images.unsplash.com/photo-1694190941111-90065ded19d8?crop=entropy\u0026cs=tinysrgb\u0026fit=max\u0026fm=jpg\u0026ixid=M3w0OTg2NjJ8MHwxfGFsbHw4fHx8fHx8Mnx8MTY5NDM0MTM2MHw\u0026ixlib=rb-4.0.3\u0026q=80\u0026w=400",
      "thumb": "https://images.unsplash.com/photo-1694190941111-90065ded19d8?crop=entropy\u0026cs=tinysrgb\u0026fit=max\u0026fm=jpg\u0026ixid=M3w0OTg2NjJ8MHwxfGFsbHw4fHx8fHx8Mnx8MTY5NDM0MTM2MHw\u0026ixlib=rb-4.0.3\u0026q=80\u0026w=200",
      "small_s3": "https://s3.us-west-2.amazonaws.com/images.unsplash.com/small/photo-1694190941111-90065ded19d8"
    },
    "links": {
      "self": "https://api.unsplash.com/photos/a-view-of-the-eiffel-tower-from-below-vIQ3GV0XRFo",
      "html": "https://unsplash.com/photos/a-view-of-the-eiffel-tower-from-below-vIQ3GV0XRFo",
      "download": "https://unsplash.com/photos/vIQ3GV0XRFo/download?ixid=M3w0OTg2NjJ8MHwxfGFsbHw4fHx8fHx8Mnx8MTY5NDM0MTM2MHw",
      "download_location": "https://api.unsplash.com/photos/vIQ3GV0XRFo/download?ixid=M3w0OTg2NjJ8MHwxfGFsbHw4fHx8fHx8Mnx8MTY5NDM0MTM2MHw"
    },
    "likes": 33,
    "liked_by_user": false,
    "current_user_collections": [],
    "sponsorship": null,
    "topic_submissions": {},
    "user": {
      "id": "zbAoUZJRd9M",
      "updated_at": "2023-09-09T16:56:04Z",
      "username": "gianp_anto94",
      "name": "Gianpaolo Antonucci",
      "first_name": "Gianpaolo",
      "last_name": "Antonucci",
      "twitter_username": "gianpa94",
      "portfolio_url": null,
      "bio": "hi everyone, my name is Gianpaolo and I am a photographer from Salerno, Italy.",
      "location": "Salerno, Italy",
      "links": {
        "self": "https://api.unsplash.com/users/gianp_anto94",
        "html": "https://unsplash.com/@gianp_anto94",
        "photos": "https://api.unsplash.com/users/gianp_anto94/photos",
        "likes": "https://api.unsplash.com/users/gianp_anto94/likes",
        "portfolio": "https://api.unsplash.com/users/gianp_anto94/portfolio",
        "following": "https://api.unsplash.com/users/gianp_anto94/following",
        "followers": "https://api.unsplash.com/users/gianp_anto94/followers"
      },
      "profile_image": {
        "small": "https://images.unsplash.com/profile-1694245902388-f4063d7f229c?ixlib=rb-4.0.3\u0026crop=faces\u0026fit=crop\u0026w=32\u0026h=32",
        "medium": "https://images.unsplash.com/profile-1694245902388-f4063d7f229c?ixlib=rb-4.0.3\u0026crop=faces\u0026fit=crop\u0026w=64\u0026h=64",
        "large": "https://images.unsplash.com/profile-1694245902388-f4063d7f229c?ixlib=rb-4.0.3\u0026crop=faces\u0026fit=crop\u0026w=128\u0026h=128"
      },
      "instagram_username": "gianpanto.arw",
      "total_collections": 0,
      "total_likes": 270,
      "total_photos": 93,
      "accepted_tos": true,
      "for_hire": false,
      "social": {
        "instagram_username": "gianpanto.arw",
        "portfolio_url": null,
        "twitter_username": "gianpa94",
        "paypal_email": null
      }
    }
  },
  {
    "id": "8B7hKTGO7OE",
    "slug": "a-black-and-white-photo-of-a-road-surrounded-by-trees-8B7hKTGO7OE",
    "created_at": "2023-08-27T18:55:54Z",
    "updated_at": "2023-09-10T00:44:16Z",
    "promoted_at": "2023-09-09T16:40:01Z",
    "width": 5557,
    "height": 5739,
    "color": "#262626",
    "blur_hash": "LYC6+9Rj00xu?bWBD%t7t7ayofay",
    "description": "asphalt road in the woods leading off into the dista",
    "alt_description": "a black and white photo of a road surrounded by trees",
    "breadcrumbs": [],
    "urls": {
      "raw": "https://images.unsplash.com/photo-1693162407368-ba8ac70d0423?ixid=M3w0OTg2NjJ8MHwxfGFsbHw5fHx8fHx8Mnx8MTY5NDM0MTM2MHw\u0026ixlib=rb-4.0.3",
      "full": "https://images.unsplash.com/photo-1693162407368-ba8ac70d0423?crop=entropy\u0026cs=srgb\u0026fm=jpg\u0026ixid=M3w0OTg2NjJ8MHwxfGFsbHw5fHx8fHx8Mnx8MTY5NDM0MTM2MHw\u0026ixlib=rb-4.0.3\u0026q=85",
      "regular": "https://images.unsplash.com/photo-1693162407368-ba8ac70d0423?crop=entropy\u0026cs=tinysrgb\u0026fit=max\u0026fm=jpg\u0026ixid=M3w0OTg2NjJ8MHwxfGFsbHw5fHx8fHx8Mnx8MTY5NDM0MTM2MHw\u0026ixlib=rb-4.0.3\u0026q=80\u0026w=1080",
      "small": "https://images.unsplash.com/photo-1693162407368-ba8ac70d0423?crop=entropy\u0026cs=tinysrgb\u0026fit=max\u0026fm=jpg\u0026ixid=M3w0OTg2NjJ8MHwxfGFsbHw5fHx8fHx8Mnx8MTY5NDM0MTM2MHw\u0026ixlib=rb-4.0.3\u0026q=80\u0026w=400",
      "thumb": "https://images.unsplash.com/photo-1693162407368-ba8ac70d0423?crop=entropy\u0026cs=tinysrgb\u0026fit=max\u0026fm=jpg\u0026ixid=M3w0OTg2NjJ8MHwxfGFsbHw5fHx8fHx8Mnx8MTY5NDM0MTM2MHw\u0026ixlib=rb-4.0.3\u0026q=80\u0026w=200",
      "small_s3": "https://s3.us-west-2.amazonaws.com/images.unsplash.com/small/photo-1693162407368-ba8ac70d0423"
    },
    "links": {
      "self": "https://api.unsplash.com/photos/a-black-and-white-photo-of-a-road-surrounded-by-trees-8B7hKTGO7OE",
      "html": "https://unsplash.com/photos/a-black-and-white-photo-of-a-road-surrounded-by-trees-8B7hKTGO7OE",
      "download": "https://unsplash.com/photos/8B7hKTGO7OE/download?ixid=M3w0OTg2NjJ8MHwxfGFsbHw5fHx8fHx8Mnx8MTY5NDM0MTM2MHw",
      "download_location": "https://api.unsplash.com/photos/8B7hKTGO7OE/download?ixid=M3w0OTg2NjJ8MHwxfGFsbHw5fHx8fHx8Mnx8MTY5NDM0MTM2MHw"
    },
    "likes": 31,
    "liked_by_user": false,
    "current_user_collections": [],
    "sponsorship": null,
    "topic_submissions": {},
    "user": {
      "id": "lS02LVqltFI",
      "updated_at": "2023-09-10T09:46:41Z",
      "username": "abalashevsky",
      "name": "Artem Balashevsky",
      "first_name": "Artem",
      "last_name": "Balashevsky",
      "twitter_username": null,
      "portfolio_url": null,
      "bio": "photography as a hobby\r\nminimal, details, nature \u003c3",
      "location": "Belarus",
      "links": {
        "self": "https://api.unsplash.com/users/abalashevsky",
        "html": "https://unsplash.com/@abalashevsky",
        "photos": "https://api.unsplash.com/users/abalashevsky/photos",
        "likes": "https://api.unsplash.com/users/abalashevsky/likes",
        "portfolio": "https://api.unsplash.com/users/abalashevsky/portfolio",
        "following": "https://api.unsplash.com/users/abalashevsky/following",
        "followers": "https://api.unsplash.com/users/abalashevsky/followers"
      },
      "profile_image": {
        "small": "https://images.unsplash.com/profile-1691525737646-af74e8d6899aimage?ixlib=rb-4.0.3\u0026crop=faces\u0026fit=crop\u0026w=32\u0026h=32",
        "medium": "https://images.unsplash.com/profile-1691525737646-af74e8d6899aimage?ixlib=rb-4.0.3\u0026crop=faces\u0026fit=crop\u0026w=64\u0026h=64",
        "large": "https://images.unsplash.com/profile-1691525737646-af74e8d6899aimage?ixlib=rb-4.0.3\u0026crop=faces\u0026fit=crop\u0026w=128\u0026h=128"
      },
      "instagram_username": "abalashevsky",
      "total_collections": 0,
      "total_likes": 17,
      "total_photos": 93,
      "accepted_tos": true,
      "for_hire": false,
      "social": {
        "instagram_username": "abalashevsky",
        "portfolio_url": null,
        "twitter_username": null,
        "paypal_email": null
      }
    }
  },
  {
    "id": "5x4d5MVWRFs",
    "slug": "a-woman-laying-in-the-grass-with-her-eyes-closed-5x4d5MVWRFs",
    "created_at": "2023-09-03T08:26:55Z",
    "updated_at": "2023-09-10T03:35:58Z",
    "promoted_at": "2023-09-09T16:32:01Z",
    "width": 3264,
    "height": 4928,
    "color": "#262626",
    "blur_hash": "LGAwF=?bIUWB00D%j[ofM{xuxuWB",
    "description": null,
    "alt_description": "a woman laying in the grass with her eyes closed",
    "breadcrumbs": [],
    "urls": {
      "raw": "https://images.unsplash.com/photo-1693729600526-2ce45d1d53cf?ixid=M3w0OTg2NjJ8MHwxfGFsbHwxMHx8fHx8fDJ8fDE2OTQzNDEzNjB8\u0026ixlib=rb-4.0.3",
      "full": "https://images.unsplash.com/photo-1693729600526-2ce45d1d53cf?crop=entropy\u0026cs=srgb\u0026fm=jpg\u0026ixid=M3w0OTg2NjJ8MHwxfGFsbHwxMHx8fHx8fDJ8fDE2OTQzNDEzNjB8\u0026ixlib=rb-4.0.3\u0026q=85",
      "regular": "https://images.unsplash.com/photo-1693729600526-2ce45d1d53cf?crop=entropy\u0026cs=tinysrgb\u0026fit=max\u0026fm=jpg\u0026ixid=M3w0OTg2NjJ8MHwxfGFsbHwxMHx8fHx8fDJ8fDE2OTQzNDEzNjB8\u0026ixlib=rb-4.0.3\u0026q=80\u0026w=1080",
      "small": "https://images.unsplash.com/photo-1693729600526-2ce45d1d53cf?crop=entropy\u0026cs=tinysrgb\u0026fit=max\u0026fm=jpg\u0026ixid=M3w0OTg2NjJ8MHwxfGFsbHwxMHx8fHx8fDJ8fDE2OTQzNDEzNjB8\u0026ixlib=rb-4.0.3\u0026q=80\u0026w=400",
      "thumb": "https://images.unsplash.com/photo-1693729600526-2ce45d1d53cf?crop=entropy\u0026cs=tinysrgb\u0026fit=max\u0026fm=jpg\u0026ixid=M3w0OTg2NjJ8MHwxfGFsbHwxMHx8fHx8fDJ8fDE2OTQzNDEzNjB8\u0026ixlib=rb-4.0.3\u0026q=80\u0026w=200",
      "small_s3": "https://s3.us-west-2.amazonaws.com/images.unsplash.com/small/photo-1693729600526-2ce45d1d53cf"
    },
    "links": {
      "self": "https://api.unsplash.com/photos/a-woman-laying-in-the-grass-with-her-eyes-closed-5x4d5MVWRFs",
      "html": "https://unsplash.com/photos/a-woman-laying-in-the-grass-with-her-eyes-closed-5x4d5MVWRFs",
      "download": "https://unsplash.com/photos/5x4d5MVWRFs/download?ixid=M3w0OTg2NjJ8MHwxfGFsbHwxMHx8fHx8fDJ8fDE2OTQzNDEzNjB8",
      "download_location": "https://api.unsplash.com/photos/5x4d5MVWRFs/download?ixid=M3w0OTg2NjJ8MHwxfGFsbHwxMHx8fHx8fDJ8fDE2OTQzNDEzNjB8"
    },
    "likes": 13,
    "liked_by_user": false,
    "current_user_collections": [],
    "sponsorship": null,
    "topic_submissions": {},
    "user": {
      "id": "kJG5PAKzWRU",
      "updated_at": "2023-09-09T16:36:03Z",
      "username": "radio_np",
      "name": "Hans Junge",
      "first_name": "Hans",
      "last_name": "Junge",
      "twitter_username": null,
      "portfolio_url": "https://www.behance.net/jackryan27",
      "bio": null,
      "location": "Ukraine",
      "links": {
        "self": "https://api.unsplash.com/users/radio_np",
        "html": "https://unsplash.com/@radio_np",
        "photos": "https://api.unsplash.com/users/radio_np/photos",
        "likes": "https://api.unsplash.com/users/radio_np/likes",
        "portfolio": "https://api.unsplash.com/users/radio_np/portfolio",
        "following": "https://api.unsplash.com/users/radio_np/following",
        "followers": "https://api.unsplash.com/users/radio_np/followers"
      },
      "profile_image": {
        "small": "https://images.unsplash.com/profile-1694031471272-2e6896979fcf?ixlib=rb-4.0.3\u0026crop=faces\u0026fit=crop\u0026w=32\u0026h=32",
        "medium": "https://images.unsplash.com/profile-1694031471272-2e6896979fcf?ixlib=rb-4.0.3\u0026crop=faces\u0026fit=crop\u0026w=64\u0026h=64",
        "large": "https://images.unsplash.com/profile-1694031471272-2e6896979fcf?ixlib=rb-4.0.3\u0026crop=faces\u0026fit=crop\u0026w=128\u0026h=128"
      },
      "instagram_username": "radio_np",
      "total_collections": 0,
      "total_likes": 8,
      "total_photos": 21,
      "accepted_tos": true,
      "for_hire": true,
      "social": {
        "instagram_username": "radio_np",
        "portfolio_url": "https://www.behance.net/jackryan27",
        "twitter_username": null,
        "paypal_email": null
      }
    }
  }
]
